g2t/__init__.py
g2t/graph2topictm.py
g2t/graph2topic/__init__.py
g2t/graph2topic/graph2topic.py
g2t/graph2topic/graphs.py
g2t/graph2topic/misc.py
g2t/graph2topic/overlap_community_detection.py
g2t/graph2topic/tfidf_idfi.py
g2t/graph2topic/backend/__init__.py
g2t/graph2topic/backend/_base.py
g2t/graph2topic/backend/_flair.py
g2t/graph2topic/backend/_sentencetransformers.py
g2t/graph2topic/backend/_utils.py
graph2topictm-2.0.dist-info/METADATA
graph2topictm-2.0.dist-info/WHEEL
graph2topictm-2.0.dist-info/license.txt
graph2topictm-2.0.dist-info/top_level.txt
graph2topictm-2.0.dist-info/RECORD
