Metadata-Version: 2.1
Name: graph2topictm
Version: 2.0
Summary: G2T is a topic model based on PLMs and community detections. more details in https://github.com/lunar-moon/Graph2Topic.git
Home-page: UNKNOWN
Author: Jiapeng Liu
Author-email: liujiapeng36@fox.mail
License: UNKNOWN
Platform: UNKNOWN
License-File: license.txt
